crackmes_dl/__init__.py
crackmes_dl/api.py
crackmes_dl/endpoints.py
crackmes_dl/main.py
crackmes_dl/payloads.py
crackmes_dl/responses.py
crackmes_dl/version.py
crackmes_dl-1.0.5.dist-info/LICENSE
crackmes_dl-1.0.5.dist-info/METADATA
crackmes_dl-1.0.5.dist-info/WHEEL
crackmes_dl-1.0.5.dist-info/entry_points.txt
crackmes_dl-1.0.5.dist-info/top_level.txt
crackmes_dl-1.0.5.dist-info/RECORD
