Metadata-Version: 2.1
Name: crackmes-dl
Version: 1.0.5
Summary: Crackmes DL
Home-page: https://github.com/nymann/crackmes-dl
Maintainer: Kristian Nymann Jakobsen
Maintainer-email: kristian@nymann.dev
Requires-Python: >=3.9
License-File: LICENSE
Requires-Dist: typer >=0.4.1
Requires-Dist: requests >=2.27.1
Requires-Dist: beautifulsoup4 >=4.11.1
Requires-Dist: pydantic <2.0.0,>=1.9.0
Provides-Extra: all
Requires-Dist: isort ; extra == 'all'
Requires-Dist: wemake-python-styleguide ; extra == 'all'
Requires-Dist: mypy ; extra == 'all'
Requires-Dist: black ; extra == 'all'
Requires-Dist: nitpick ; extra == 'all'
Requires-Dist: add-trailing-comma ; extra == 'all'
Requires-Dist: types-requests >=2.27.17 ; extra == 'all'
Requires-Dist: types-beautifulsoup4 >=4.10.19 ; extra == 'all'
Requires-Dist: devtools[pygmentz] ; extra == 'all'
Requires-Dist: pytest ; extra == 'all'
Requires-Dist: pytest-cov ; extra == 'all'
Requires-Dist: pytest-mock ; extra == 'all'
Provides-Extra: dev
Requires-Dist: isort ; extra == 'dev'
Requires-Dist: wemake-python-styleguide ; extra == 'dev'
Requires-Dist: mypy ; extra == 'dev'
Requires-Dist: black ; extra == 'dev'
Requires-Dist: nitpick ; extra == 'dev'
Requires-Dist: add-trailing-comma ; extra == 'dev'
Requires-Dist: types-requests >=2.27.17 ; extra == 'dev'
Requires-Dist: types-beautifulsoup4 >=4.10.19 ; extra == 'dev'
Requires-Dist: devtools[pygmentz] ; extra == 'dev'
Provides-Extra: tests
Requires-Dist: pytest ; extra == 'tests'
Requires-Dist: pytest-cov ; extra == 'tests'
Requires-Dist: pytest-mock ; extra == 'tests'
